client/__init__.py
client/client.py
client/client_app/__init__.py
client/client_app/add_contact.py
client/client_app/client_db.py
client/client_app/del_contact.py
client/client_app/main_window.py
client/client_app/main_window_conv.py
client/client_app/start_dialog.py
client/client_app/transport.py
client/common/__init__.py
client/common/descriptors.py
client/common/errors.py
client/common/helper.py
client/common/log_decorator.py
client/common/metacls.py
client/common/utils.py
client/common/variables.py
client/logs/__init__.py
client/logs/client_log_config.py
client/logs/server_log_config.py
client/unit_tests/__init__.py
jimm_chat_client-0.1.1.dist-info/METADATA
jimm_chat_client-0.1.1.dist-info/WHEEL
jimm_chat_client-0.1.1.dist-info/top_level.txt
jimm_chat_client-0.1.1.dist-info/RECORD
